Metadata-Version: 2.1
Name: WhamBamPy
Version: 0.0.7
Summary: WHM Api interface
Home-page: http://pypi.python.org/pypi/whambampy/
Download-URL: https://github.com/BBDM-Group/bbdm-whm-manager/archive/refs/tags/0.0.7.tar.gz
Author: Dmitry Minin
Author-email: dmitry.m@bbdmgroup.com
License: LICENSE.txt
License-File: LICENSE.txt
